{
  "fallback": "minecraft:empty",
  "elements": [
    {"element":{"element_type":"minecraft:single_pool_element","processors":"minecraft:empty","location":"megamod:village/snowy/sanctuary","projection":"rigid"},"weight":2},{"element":{"element_type":"minecraft:single_pool_element","processors":"minecraft:empty","location":"megamod:village/snowy/barracks","projection":"rigid"},"weight":2},{"element":{"element_type":"minecraft:single_pool_element","processors":"minecraft:empty","location":"megamod:village/snowy/archery_range_large","projection":"rigid"},"weight":1},{"element":{"element_type":"minecraft:single_pool_element","processors":"minecraft:empty","location":"megamod:village/snowy/archery_range_small","projection":"rigid"},"weight":2},{"element":{"element_type":"minecraft:single_pool_element","processors":"minecraft:empty","location":"megamod:village/snowy/wizard_tower","projection":"rigid"},"weight":2},{"element":{"element_type":"minecraft:single_pool_element","processors":"minecraft:empty","location":"megamod:village/snowy/jewelry_shop","projection":"rigid"},"weight":1}
  ]
}
