{
  "name": "megamod:shire/buildings",
  "fallback": "megamod:shire/roads",
  "elements": [
    {
      "weight": 10,
      "element": {
        "location": "megamod:shire/builder1",
        "processors": "megamod:shire/placeholder_replacement",
        "projection": "rigid",
        "element_type": "minecraft:single_pool_element"
      }
    },
    {
      "weight": 1,
      "element": {
        "location": "megamod:shire/builder2",
        "processors": "megamod:shire/placeholder_replacement",
        "projection": "rigid",
        "element_type": "minecraft:single_pool_element"
      }
    },
    {
      "weight": 5,
      "element": {
        "location": "megamod:shire/courieralt1",
        "processors": "megamod:shire/placeholder_replacement",
        "projection": "rigid",
        "element_type": "minecraft:single_pool_element"
      }
    },
    {
      "weight": 1,
      "element": {
        "location": "megamod:shire/courieralt2",
        "processors": "megamod:shire/placeholder_replacement",
        "projection": "rigid",
        "element_type": "minecraft:single_pool_element"
      }
    },
    {
      "weight": 3,
      "element": {
        "location": "megamod:shire/restaurant1",
        "processors": "megamod:shire/placeholder_replacement",
        "projection": "rigid",
        "element_type": "minecraft:single_pool_element"
      }
    },
    {
      "weight": 1,
      "element": {
        "location": "megamod:shire/restaurant2",
        "processors": "megamod:shire/placeholder_replacement",
        "projection": "rigid",
        "element_type": "minecraft:single_pool_element"
      }
    },
    {
      "weight": 10,
      "element": {
        "location": "megamod:shire/farm1",
        "processors": "megamod:shire/placeholder_replacement",
        "projection": "rigid",
        "element_type": "minecraft:single_pool_element"
      }
    },
    {
      "weight": 1,
      "element": {
        "location": "megamod:shire/farm2",
        "processors": "megamod:shire/placeholder_replacement",
        "projection": "rigid",
        "element_type": "minecraft:single_pool_element"
      }
    },
    {
      "weight": 1,
      "element": {
        "location": "megamod:shire/tavern1",
        "processors": "megamod:shire/placeholder_replacement",
        "projection": "rigid",
        "element_type": "minecraft:single_pool_element"
      }
    },
    {
      "weight": 12,
      "element": {
        "location": "megamod:shire/guardtower1",
        "processors": "megamod:shire/placeholder_replacement",
        "projection": "rigid",
        "element_type": "minecraft:single_pool_element"
      }
    },
    {
      "weight": 1,
      "element": {
        "location": "megamod:shire/guardtower2",
        "processors": "megamod:shire/placeholder_replacement",
        "projection": "rigid",
        "element_type": "minecraft:single_pool_element"
      }
    },
    {
      "weight": 10,
      "element": {
        "location": "megamod:shire/house1",
        "processors": "megamod:shire/placeholder_replacement",
        "projection": "rigid",
        "element_type": "minecraft:single_pool_element"
      }
    },
    {
      "weight": 1,
      "element": {
        "location": "megamod:shire/house2",
        "processors": "megamod:shire/placeholder_replacement",
        "projection": "rigid",
        "element_type": "minecraft:single_pool_element"
      }
    },
    {
      "weight": 5,
      "element": {
        "location": "megamod:shire/mine1",
        "processors": "megamod:shire/placeholder_replacement",
        "projection": "rigid",
        "element_type": "minecraft:single_pool_element"
      }
    },
    {
      "weight": 1,
      "element": {
        "location": "megamod:shire/mine2",
        "processors": "megamod:shire/placeholder_replacement",
        "projection": "rigid",
        "element_type": "minecraft:single_pool_element"
      }
    },
    {
      "weight": 5,
      "element": {
        "location": "megamod:shire/warehouse1",
        "processors": "megamod:shire/placeholder_replacement",
        "projection": "rigid",
        "element_type": "minecraft:single_pool_element"
      }
    },
    {
      "weight": 20,
      "element": {
        "element_type": "minecraft:empty_pool_element"
      }
    }
  ]
}