{
  "display": {
    "icon": {
      "id": "wizards:wand_frost"
    },
    "title": {
      "translate": "advancements.rpg_series.spell_cast_frost_wand.title"
    },
    "description": {
      "translate": "advancements.rpg_series.spell_cast_frost_wand.description"
    },
    "frame": "task",
    "show_toast": false,
    "announce_to_chat": false,
    "hidden": false
  },
  "parent": "rpg_series:path_choose_frost",
  "criteria": {
    "cast": {
      "trigger": "spell_engine:spell_cast",
      "conditions": {
        "spell": "wizards:frost_shard"
      }
    }
  },
  "requirements": [
    [
      "cast"
    ]
  ]
}