{
  "values": [
    {
      "id": "relics_rpgs:jewel_figurine_sapphire",
      "required": false
    },
    {
      "id": "relics_rpgs:jewel_figurine_tanzanite",
      "required": false
    },
    {
      "id": "relics_rpgs:medium_proc_spell_haste",
      "required": false
    },
    {
      "id": "relics_rpgs:greater_perk_defense_block",
      "required": false
    },
    {
      "id": "relics_rpgs:greater_healing_taken",
      "required": false
    },
    {
      "id": "relics_rpgs:greater_perk_melee_stun",
      "required": false
    },
    {
      "id": "relics_rpgs:jewel_figurine_citrine",
      "required": false
    },
    {
      "id": "relics_rpgs:greater_perk_heal_cleanse",
      "required": false
    },
    {
      "id": "relics_rpgs:medium_proc_spell_power",
      "required": false
    },
    {
      "id": "relics_rpgs:greater_perk_roll_damage",
      "required": false
    },
    {
      "id": "relics_rpgs:medium_proc_defense",
      "required": false
    },
    {
      "id": "relics_rpgs:medium_proc_attack_damage",
      "required": false
    },
    {
      "id": "relics_rpgs:lesser_evasion",
      "required": false
    },
    {
      "id": "relics_rpgs:jewel_figurine_topaz",
      "required": false
    },
    {
      "id": "relics_rpgs:superior_use_zone_healing_taken",
      "required": false
    },
    {
      "id": "relics_rpgs:lesser_proc_spell_crit",
      "required": false
    },
    {
      "id": "relics_rpgs:superior_use_area_attack_damage",
      "required": false
    },
    {
      "id": "relics_rpgs:lesser_proc_arcane_fire",
      "required": false
    },
    {
      "id": "relics_rpgs:medium_proc_evasion",
      "required": false
    },
    {
      "id": "relics_rpgs:jewel_figurine_ruby",
      "required": false
    },
    {
      "id": "relics_rpgs:lesser_melee_crit_chance",
      "required": false
    },
    {
      "id": "relics_rpgs:greater_perk_shield_reset",
      "required": false
    },
    {
      "id": "relics_rpgs:superior_use_area_defense_health",
      "required": false
    },
    {
      "id": "relics_rpgs:greater_perk_spell_stun",
      "required": false
    },
    {
      "id": "relics_rpgs:lesser_melee_crit_damage",
      "required": false
    },
    {
      "id": "relics_rpgs:lesser_use_dex",
      "required": false
    },
    {
      "id": "relics_rpgs:medium_proc_frost_power",
      "required": false
    },
    {
      "id": "relics_rpgs:lesser_use_spell_haste",
      "required": false
    },
    {
      "id": "relics_rpgs:lesser_use_damage",
      "required": false
    },
    {
      "id": "relics_rpgs:lesser_use_spell_power",
      "required": false
    },
    {
      "id": "relics_rpgs:medium_proc_ranged_damage",
      "required": false
    },
    {
      "id": "relics_rpgs:lesser_proc_crit_damage",
      "required": false
    },
    {
      "id": "relics_rpgs:medium_proc_healing_power",
      "required": false
    },
    {
      "id": "relics_rpgs:lesser_proc_frost_healing",
      "required": false
    },
    {
      "id": "relics_rpgs:lesser_roll",
      "required": false
    },
    {
      "id": "relics_rpgs:superior_use_zone_spell_power",
      "required": false
    },
    {
      "id": "relics_rpgs:medium_proc_arcane_power",
      "required": false
    },
    {
      "id": "relics_rpgs:jewel_figurine_jade",
      "required": false
    },
    {
      "id": "relics_rpgs:lesser_use_ranged",
      "required": false
    },
    {
      "id": "relics_rpgs:greater_perk_evasion_attack",
      "required": false
    },
    {
      "id": "relics_rpgs:medium_proc_attack_speed",
      "required": false
    },
    {
      "id": "relics_rpgs:medium_proc_fire_power",
      "required": false
    },
    {
      "id": "relics_rpgs:greater_perk_ranged_levitate",
      "required": false
    },
    {
      "id": "relics_rpgs:lesser_use_health",
      "required": false
    }
  ]
}